redash_iodide/__init__.py
redash_iodide/resources.py
redash_iodide/settings.py
redash_iodide/explore/__init__.py
redash_iodide/explore/extension.py
redash_iodide/explore/iodide-notebook.iomd.j2
redash_iodide/explore/bundle/IodideButton.jsx
redash_iodide-2020.1.0.dist-info/LICENSE
redash_iodide-2020.1.0.dist-info/METADATA
redash_iodide-2020.1.0.dist-info/WHEEL
redash_iodide-2020.1.0.dist-info/entry_points.txt
redash_iodide-2020.1.0.dist-info/top_level.txt
redash_iodide-2020.1.0.dist-info/RECORD
