Metadata-Version: 2.1
Name: redash-iodide
Version: 2020.1.0
Summary: Extensions to Redash for Iodide by Mozilla
Home-page: UNKNOWN
Author: Mozilla Foundation
Author-email: dev-webdev@lists.mozilla.org
License: MPL-2.0
Project-URL: homepage, https://github.com/iodide-project/redash-iodide
Platform: UNKNOWN
Classifier: Development Status :: 5 - Production/Stable
Classifier: Environment :: Web Environment :: Mozilla
Classifier: Framework :: Django
Classifier: Intended Audience :: Developers
Classifier: License :: OSI Approved :: Mozilla Public License 2.0 (MPL 2.0)
Classifier: Programming Language :: Python
Classifier: Programming Language :: Python :: 2
Classifier: Programming Language :: Python :: 2.7
Classifier: Programming Language :: Python :: 3
Classifier: Programming Language :: Python :: 3.4
Classifier: Programming Language :: Python :: 3.5
Classifier: Programming Language :: Python :: 3.6
Classifier: Programming Language :: Python :: 3.7
Classifier: Programming Language :: Python :: 3.8
Classifier: Topic :: Internet :: WWW/HTTP
Requires-Dist: requests
Requires-Dist: six
Provides-Extra: dev
Requires-Dist: watchdog ; extra == 'dev'
Provides-Extra: test
Requires-Dist: flake8 (==3.5.0) ; extra == 'test'
Requires-Dist: mock ; extra == 'test'
Requires-Dist: pytest ; extra == 'test'
Requires-Dist: pytest-cov ; extra == 'test'
Requires-Dist: pytest-flake8 (<1.0.1) ; extra == 'test'
